{
  "name": "Martha Spencer",
  "age": 45,
  "address": {
    "street": "Cired Ridge",
    "city": "Cokehhog",
    "state": "DE",
    "zip": "48998"
  },
  "contact": {
    "phone": "(672) 687-1519",
    "servicePhone": "800316175"
  },
  "birthday": "1971-06-26T07:13:14.566Z",
  "ip": "68.167.197.254",
  "foo": "bar",
  "profile": {
    "about": "Siab okbusa hutwimub odifa gozonvoj homuh doho neh ol ke lael wi mumomza gor. Hab cez juk ni leg egodo hugfib loh hilehva wu radipku ed. Pesedoz gibliz jan udagiwzo era to upazi ati momlo ca gomotec ser gappegag fahawzap debwat lulzaluhe ro bepiza. Lebajnun saot lat nunanfe we nuhve cesmuap roib obetod padavuw dujko vudjigniw reavudu. Ag koke fe dejluri za badju usubeta ehulo ne ta ketvolrih holkov zajef bodfege ep firzuhmi capu samjohda.",
    "bio": "Faw alu wokben tas cep ivnog eze cogadzag wo ane ce sujaecu mes el zoz uhsu bebguk. Mardo dufeluk ketuhi zuwuv hadal pabo nakfu canafe ijdevwar me zifnadeh ulohib ponop hotrej bel iv la wu. Zobde su anwuku noikiza gazumeg howuki senkok povger sirvesaz nucjif nudvuva upoip ut ajisja. Muf hu reorenu suvlat ucegu uzci catmof otehov sosozo cauci ji tuzih ir. Dehci hohoni hisiduw hi ar jecisu worme mide gacmigok wul ceklag gemefo. Fi bo daz ip tahe pibmal de ilva duj iwmipep ma widnum jizinib bajozo ruw ozitebrej nan."
  },
  "apiKey": "e0d8d0bd5f69c1badef986d868afa792a3ece18756997b3f1a8934e18bd39274",
  "currency": {
    "code": "KMF",
    "name": "Comoros Franc"
  }
}